{
  "id": "result_제22대국회 제427회(임시회) 제2차 산업통상자원중소벤처기업위원회(전체회의) (2025.07.15.)_chunk_16",
  "source_dir": "result_제22대국회 제427회(임시회) 제2차 산업통상자원중소벤처기업위원회(전체회의) (2025.07.15.)",
  "notion_output": {
    "project_name": "AI 기반 소상공인 지원 프로젝트",
    "project_purpose": "소상공인의 경영 및 사회안전망을 강화하여 경영의 안정성과 활성화를 도모하고, 소상공인의 혁신 의지를 유지하기 위해 AI 기반의 지원 시스템을 구축하고 운영합니다.",
    "project_period": "2024년 1월 ~ 2025년 12월",
    "project_manager": "김철수",
    "core_objectives": [
      "소상공인의 경영 및 사회안전망 강화",
      "소상공인의 혁신 의지 유지",
      "AI 기반의 지원 시스템 구축 및 운영"
    ],
    "core_idea": "AI 기반의 소상공인 지원 시스템을 구축하여 경영 및 사회안전망을 강화하고, 혁신 의지를 유지하도록 지원합니다.",
    "idea_description": "소상공인의 경영 및 사회안전망을 강화하기 위해 AI 기반의 지원 시스템을 구축하고 운영합니다. 이 시스템은 소상공인의 경영 데이터를 분석하여 개인화된 조언을 제공하고, 사회안전망의 필요성을 판단하여 보험 및 지원을 제공합니다.",
    "execution_plan": "1. AI 기반의 소상공인 지원 시스템 개발 및 테스트 (2024년 1월 ~ 2024년 6월)\n2. 시범 운영 및 피드백 수집 (2024년 7월 ~ 2024년 12월)\n3. 전국적으로 확대 시행 (2025년 1월 ~ 2025년 12월)",
    "expected_effects": [
      "소상공인의 경영 효율성 향상",
      "소상공인의 사회안전망 이용률 증가",
      "소상공인의 혁신 의지 유지 및 활성화"
    ]
  },
  "metadata": {
    "source_file": "../Raw_Data_val/result_제22대국회 제427회(임시회) 제2차 산업통상자원중소벤처기업위원회(전체회의) (2025.07.15.)/05_final_result.json",
    "is_chunk": true,
    "chunk_index": 16,
    "total_chunks": 26,
    "processing_date": "2025-08-10T11:47:03.809109"
  }
}