{
  "id": "result_제22대국회 제427회(임시회) 제2차 산업통상자원중소벤처기업위원회(전체회의) (2025.07.15.)_chunk_14",
  "source_dir": "result_제22대국회 제427회(임시회) 제2차 산업통상자원중소벤처기업위원회(전체회의) (2025.07.15.)",
  "notion_output": {
    "project_name": "농업자원 효율화 및 주말농장 개발 프로젝트",
    "project_purpose": "농지 자원의 효율적 활용 및 주말농장 개발을 통해 지역경제 활성화 및 농업인 소득 증대",
    "project_period": "2024.01.01 ~ 2024.12.31",
    "project_manager": "한성숙",
    "core_objectives": [
      "목표 1: 농지 자원의 효율적 활용을 위한 농업경영계획서 제출 및 자경 확보",
      "목표 2: 주말농장 운영을 통한 지역 관광 및 소비 증대",
      "목표 3: 농업인의 소득 증대 및 농촌 경제 활성화"
    ],
    "core_idea": "농지 자원의 효율적 활용을 통해 농업과 관광 산업의 융합을 추진",
    "idea_description": "농지를 주말농장으로 활용하여 지역 관광객을 유치하고, 이를 통해 농업인의 소득을 증대시키며, 농업과 관광 산업의 융합을 도모한다.",
    "execution_plan": "1단계: 농지 자원 평가 및 농업경영계획서 제출 (2024.01.01 ~ 2024.03.31)\n2단계: 주말농장 설계 및 구축 (2024.04.01 ~ 2024.06.30)\n3단계: 주말농장 운영 및 관광 마케팅 (2024.07.01 ~ 2024.12.31)",
    "expected_effects": [
      "기대효과 1: 농지 자원의 효율적 활용으로 농업 생산성 향상",
      "기대효과 2: 주말농장 운영으로 지역 관광객 유치 및 소비 증대",
      "기대효과 3: 농업인의 소득 증대 및 지역경제 활성화"
    ]
  },
  "metadata": {
    "source_file": "Raw_Data_val/result_제22대국회 제427회(임시회) 제2차 산업통상자원중소벤처기업위원회(전체회의) (2025.07.15.)/05_final_result.json",
    "utterance_count": 2167,
    "speakers": [
      "박성민 위원",
      "서일준 위원",
      "위원장 이철규",
      "서왕진 위원",
      "장철민 위원",
      "김성원 위원",
      "이재관 위원",
      "중소벤처기업부장관후보자 한성숙",
      "김종민 위원",
      "곽상언 위원",
      "이언주 위원",
      "김한규 위원",
      "강승규 위원",
      "박상웅 위원",
      "오세희 위원",
      "김원이 위원",
      "나경원 위원",
      "권향엽 위원",
      "허성무 위원",
      "구자근 위원",
      "정동만 위원",
      "송재봉 위원",
      "이종배 위원",
      "김정호 위원",
      "김동아 위원",
      "박형수 위원",
      "증인 오세윤",
      "박지혜 위원",
      "정진욱 위원",
      "허종식 위원"
    ],
    "original_length": 115811,
    "chunking_info": {
      "is_chunked": true,
      "total_chunks": 26
    },
    "is_chunk": true,
    "chunk_index": 14,
    "processing_date": "2025-08-09T21:22:15.143388"
  }
}