{
  "id": "result_Bmr012_chunk_5",
  "source_dir": "result_Bmr012",
  "notion_output": {
    "project_name": "헤드셋 커넥터 및 전자 회로 개선 프로젝트",
    "project_purpose": "헤드셋의 커넥터 문제를 해결하고 전자 회로를 개선하여 사용자 경험을 향상시키며, 다양한 헤드셋 옵션을 제공함",
    "project_period": "2025.01.01 ~ 2025.03.31",
    "project_manager": "Speaker_D",
    "core_objectives": [
      "목표 1: 헤드셋 커넥터 문제 해결 및 대체 솔루션 제공",
      "목표 2: 피그테일 헤드셋 납땜 및 사용 가능 여부 확인",
      "목표 3: 왕관 CM 311 AE 헤드셋의 가격 및 성능 평가",
      "목표 4: NIST와의 협력으로 전사 표준 개발",
      "목표 5: Echocancellation 기술 적용 및 대화 중 겹치는 기간 처리"
    ],
    "core_idea": "헤드셋의 커넥터 문제를 해결하기 위한 대체 솔루션과 전자 회로 개선 방안을 마련하고, 다양한 헤드셋 옵션을 통해 사용자 선택권 확대",
    "idea_description": "소니의 독점 커넥터 문제를 해결하기 위해 피그테일 헤드셋 납땜 및 왕관 CM 311 AE 헤드셋 사용을 고려하며, NIST와의 협력을 통해 전사 표준을 개발하고, Echocancellation 기술을 적용하여 대화 중 겹치는 기간을 처리함",
    "execution_plan": "1단계: 헤드셋 커넥터 문제 분석 및 대체 솔루션 검토 (2025.01.01 ~ 2025.01.15)\n2단계: 피그테일 헤드셋 납땜 및 사용 가능성 확인 (2025.01.16 ~ 2025.02.15)\n3단계: 왕관 CM 311 AE 헤드셋의 가격 및 성능 평가 (2025.02.16 ~ 2025.02.31)\n4단계: NIST와의 협력으로 전사 표준 개발 (2025.03.01 ~ 2025.03.15)\n5단계: Echocancellation 기술 적용 및 테스트 (2025.03.16 ~ 2025.03.31)",
    "expected_effects": [
      "기대효과 1: 헤드셋 커넥터 문제 해결로 인한 사용자 만족도 증가",
      "기대효과 2: 다양한 헤드셋 옵션 제공으로 인한 고객 선택권 확대",
      "기대효과 3: 전사 표준 개발로 인한 데이터 처리 효율성 향상",
      "기대효과 4: Echocancellation 기술 적용으로 인한 대화 중 겹치는 기간 처리 능력 강화"
    ]
  },
  "metadata": {
    "source_file": "../Raw_Data_val/result_Bmr012/05_final_result.json",
    "utterance_count": 602,
    "speakers": [
      "Speaker_G",
      "Speaker_H",
      "Speaker_C",
      "Speaker_D",
      "Speaker_I",
      "Speaker_F",
      "Speaker_B",
      "Speaker_A",
      "Speaker_E"
    ],
    "original_length": 20997,
    "chunking_info": {
      "is_chunked": true,
      "total_chunks": 5
    },
    "is_chunk": true,
    "chunk_index": 5,
    "processing_date": "2025-08-10T09:30:44.727732"
  }
}