{
  "id": "result_제22대국회 제427회(임시회) 제2차 기획재정위원회(전체회의) (2025.07.15.)_chunk_22",
  "source_dir": "result_제22대국회 제427회(임시회) 제2차 기획재정위원회(전체회의) (2025.07.15.)",
  "notion_output": {
    "project_name": "국세청 세무행정 효율화 및 세무사 혁신 프로젝트",
    "project_purpose": "국세청의 세무행정을 효율화하고 세무사의 역할을 강화하여 국민 세금 신뢰도를 높이며, 세무행정의 공정성을 강화한다.",
    "project_period": "2024.01.01 ~ 2024.12.31",
    "project_manager": "임광현",
    "core_objectives": [
      "목표 1: 세무행정의 효율성 및 공정성 강화",
      "목표 2: 세무사의 역할 강화 및 세무사 자격 확보",
      "목표 3: 세무행정의 디지털화 및 자동화 추진"
    ],
    "core_idea": "세무행정의 효율성과 공정성을 높이기 위해 세무사의 역할을 강화하고, 디지털화를 통해 세무행정을 혁신한다.",
    "idea_description": "세무사의 역할을 강화하여 세무행정의 신뢰성을 높이고, 디지털화를 통해 세무행정의 효율성을 극대화한다. 이를 통해 세무행정의 공정성과 신뢰성을 강화하고, 국민 세금 신뢰도를 높인다.",
    "execution_plan": "1단계: 세무사의 역할 강화 및 자격 확보 (2024.01.01 ~ 2024.03.31)\n2단계: 세무행정 디지털화 및 자동화 설계 (2024.04.01 ~ 2024.06.30)\n3단계: 디지털화 시스템 구축 및 테스트 (2024.07.01 ~ 2024.09.30)\n4단계: 디지털화 시스템 운영 및 피드백 수집 (2024.10.01 ~ 2024.12.31)",
    "expected_effects": [
      "기대효과 1: 세무행정의 효율성 증가로 인한 세무비용 절감",
      "기대효과 2: 세무사의 역할 강화로 인한 세무행정의 신뢰성 향상",
      "기대효과 3: 디지털화를 통한 세무행정의 투명성 및 공정성 강화"
    ]
  },
  "metadata": {
    "source_file": "Raw_Data_val/result_제22대국회 제427회(임시회) 제2차 기획재정위원회(전체회의) (2025.07.15.)/05_final_result.json",
    "utterance_count": 1686,
    "speakers": [
      "김태년 위원",
      "권영세 위원",
      "안도걸 위원",
      "천하람 위원",
      "김영진 위원",
      "박성훈 위원",
      "진성준 위원",
      "조승래 위원",
      "오기형 위원",
      "위원장대리 박수영",
      "박대출 위원",
      "김영환 위원",
      "위원장 임이자",
      "박수영 위원",
      "박홍근 위원",
      "이인선 위원",
      "국세청장후보자 임광현",
      "정일영 위원",
      "유상범 위원",
      "차규근 위원",
      "최기상 위원",
      "최은석 위원",
      "정태호 위원",
      "윤영석 위원"
    ],
    "original_length": 99066,
    "chunking_info": {
      "is_chunked": true,
      "total_chunks": 23
    },
    "is_chunk": true,
    "chunk_index": 22,
    "processing_date": "2025-08-09T21:23:08.315227"
  }
}