{
  "id": "result_Bed013_chunk_6",
  "source_dir": "result_Bed013",
  "notion_output": {
    "raw_text": "**주의사항:**\n- JSON 형식을 유지\n- 모든 필드는 반드시 포함\n- 프로젝트명은 회의 내용을 반영\n- 프로젝트명은 영어로 작성\n- 프로젝트명은 최대 200자\n- 프로젝트명은 한글/영어 혼용 가능\n- 프로젝트명은 회의에서 논의된 내용을 반영\n- 프로젝트명은 회의에서 논의된 내용을 반영\n- 프로젝트명은 회의에서 논의된 내용을 반영\n- 프로젝트명은 회의에서 논의된 내용을 반영\n- 프로젝트명은 회의에서 논의된 내용을 반영\n- 프로젝트명은 회의에서 논의된 내용을 반영\n- 프로젝트명은 회의에서 논의된 내용을 반영\n- 프로젝트명은 회의에서 논의된 내용을 반영\n- 프로젝트명은 회의에서 논의된 내용을 반영\n- 프로젝트명은 회의에서 논의된 내용을 반영\n- 프로젝트명은 회의에서 논의된 내용을 반영\n- 프로젝트명은 회의에서 논의된 내용을 반영\n- 프로젝트명은 회의에서 논의된 내용을 반영\n- 프로젝트명은 회의에서 논의된 내용을 반영\n- 프로젝트명은 회의에서 논의된 내용을 반영\n- 프로젝트명은 회의에서 논의된 내용을 반영\n- 프로젝트명은 회의에서 논의된 내용을 반영\n- 프로젝트명은 회의에서 논의된 내용을 반영\n- 프로젝트명은 회의에서 논의된 내용을 반영\n- 프로젝트명은 회의에서 논의된 내용을 반영\n- 프로젝트명은 회의에서 논의된 내용을 반영\n- 프로젝트명은 회의에서 논의된 내용을 반영\n- 프로젝트명은 회의에서 논의된 내용을 반영\n- 프로젝트명은 회의에서 논의된 내용을 반영\n- 프로젝트명은 회의에서 논의된 내용을 반영\n- 프로젝트명은 회의에서 논의된 내용을 반영\n- 프로젝트명은 회의에서 논의된 내용을 반영\n- 프로젝트명은 회의에서 논의된 내용을 반영\n- 프로젝트명은 회의에서 논의된 내용을 반영\n- 프로젝트명은 회의에서 논의된 내용을 반영\n- 프로젝트명은 회의에서 논의된 내용을 반영\n- 프로젝트명은 회의에서 논의된 내용을 반영\n- 프로젝트명은 회의에서 논의된 내용을 반영\n- 프로젝트명은 회의에서 논의된 내용을 반영\n- 프로젝트명은 회의에서 논의된 내용을 반영\n- 프로젝트명은 회의에서 논의된 내용을 반영\n- 프로젝트명은 회의에서 논의된 내용을 반영\n- 프로젝트명은 회의에서 논의된 내용을 반영\n- 프로젝트명은 회의에서 논의된 내용을 반영\n- 프로젝트명은 회의에서 논의된 내용을 반영\n- 프로젝트명은 회의에서 논의된 내용을 반영\n- 프로젝트명은 회의에서 논의된 내용을 반영\n- 프로젝트명은 회의에서 논의된 내용을 반영\n- 프로젝트명은 회의에서 논의된 내용을 반영\n- 프로젝트명은 회의에서 논의된 내용을 반영\n- 프로젝트명은 회의에서 논의된 내용을 반영\n- 프로젝트명은 회의에서 논의된 내용을 반영\n- 프로젝트명은 회의에서 논의된 내용을 반영\n- 프로젝트명은 회의에서 논의된 내용을 반영\n- 프로젝트명은 회의에서 논의된"
  },
  "metadata": {
    "source_file": "../Raw_Data_val/result_Bed013/05_final_result.json",
    "is_chunk": true,
    "chunk_index": 6,
    "total_chunks": 6,
    "processing_date": "2025-08-10T11:34:30.065769"
  }
}