{
  "id": "result_제22대국회 제427회(임시회) 제2차 농림축산식품해양수산위원회(전체회의) (2025.07.14.)_chunk_4",
  "source_dir": "result_제22대국회 제427회(임시회) 제2차 농림축산식품해양수산위원회(전체회의) (2025.07.14.)",
  "notion_output": {
    "project_name": "해양수산 및 수산 정책 개선 및 관리 프로젝트",
    "project_purpose": "해양수산 관련 정책의 실현 가능성 및 공청회 의견 반영을 통한 체계적 개선 계획 수립",
    "project_period": "2025.01.01 ~ 2025.03.31",
    "project_manager": "문대림 위원",
    "core_objectives": [
      "해양수산 정책의 실현 가능성 및 공청회 의견 반영을 통한 정책 개선",
      "차량 과태료 문제와 내항선원 근로소득 비과세 문제에 대한 정책적 대응",
      "해양수산 및 수산 분야의 종합적 정책적·예산적·법적 배려 강화"
    ],
    "core_idea": "해양수산 정책의 실현 가능성과 공청회 의견 반영을 통한 정책 개선을 목표로, 차량 과태료 문제와 내항선원 근로소득 비과세 문제에 대한 정책적 대응을 포함한 종합적 개선 계획을 수립",
    "idea_description": "해양수산 정책의 실현 가능성과 공청회 의견 반영을 통한 정책 개선을 목표로, 차량 과태료 문제와 내항선원 근로소득 비과세 문제에 대한 정책적 대응을 포함한 종합적 개선 계획을 수립. 해양수산 및 수산 분야의 종합적 정책적·예산적·법적 배려 강화를 통해 정책적 신뢰도를 높이기 위한 계획",
    "execution_plan": [
      {
        "task": "공청회 의견 분석 및 정책 개선 방향 수립",
        "responsible_party": "문대림 위원, 전재수 후보자",
        "deadline": "2025.01.15",
        "priority": "고"
      },
      {
        "task": "차량 과태료 문제 및 내항선원 근로소득 비과세 문제 대응 방안 수립",
        "responsible_party": "전재수 후보자, 서삼석 위원",
        "deadline": "2025.01.30",
        "priority": "중"
      },
      {
        "task": "해양수산 및 수산 분야의 종합적 정책적·예산적·법적 배려 강화 방안 수립",
        "responsible_party": "전재수 후보자, 서삼석 위원",
        "deadline": "2025.02.15",
        "priority": "중"
      },
      {
        "task": "정책 개선 계획의 검토 및 최종 확정",
        "responsible_party": "문대림 위원, 전재수 후보자",
        "deadline": "2025.03.01",
        "priority": "저"
      }
    ],
    "expected_effects": [
      "공청회 의견 반영을 통한 정책의 실현 가능성 향상",
      "차량 과태료 문제와 내항선원 근로소득 비과세 문제에 대한 정책적 대응 강화",
      "해양수산 및 수산 분야의 종합적 정책적·예산적·법적 배려 강화로 신뢰도 향상",
      "해양수산 정책의 체계적 개선 및 공청회 참여로 정책적 신뢰도 향상",
      "해양수산 및 수산 분야의 정책적·예산적·법적 배려 강화로 정책적 신뢰도 향상"
    ]
  },
  "metadata": {
    "source_file": "Raw_Data_val/result_제22대국회 제427회(임시회) 제2차 농림축산식품해양수산위원회(전체회의) (2025.07.14.)/05_final_result.json",
    "utterance_count": 1700,
    "speakers": [
      "윤준병 위원",
      "참고인 이상국",
      "서천호 위원",
      "문대림 위원",
      "송옥주 위원",
      "임호선 위원",
      "농림축산식품부장관 송미령",
      "문금주 위원",
      "이원택 위원",
      "전종덕 위원",
      "해양수산부장관후보자 전재수",
      "조승환 위원",
      "이만희 위원",
      "조경태 위원",
      "정희용 위원",
      "김선교 위원",
      "임미애 위원",
      "이병진 위원",
      "주철현 위원",
      "소위원장 이원택",
      "위원장 어기구",
      "강명구 위원",
      "서삼석 위원"
    ],
    "original_length": 102617,
    "chunking_info": {
      "is_chunked": true,
      "total_chunks": 23
    },
    "is_chunk": true,
    "chunk_index": 4,
    "processing_date": "2025-08-10T22:33:46.835612"
  }
}