{
  "id": "result_제22대국회 제426회(임시회) 제1차 과학기술정보방송통신위원회(예산결산심사소위원회) (2025.06.27.)_chunk_1",
  "source_dir": "result_제22대국회 제426회(임시회) 제1차 과학기술정보방송통신위원회(예산결산심사소위원회) (2025.06.27.)",
  "notion_output": {
    "project_name": "2025년도 제2회 추가경정예산안 심사 및 조정 프로젝트",
    "project_purpose": "2025년도 제2회 추가경정예산안의 효율적 심사 및 정부·의원 간 협의를 통한 예산 조정을 통해 과학기술 분야 연구 및 인프라 구축에 효과적으로 자원을 배분하는 것을 목표로 합니다.",
    "project_period": "2025.01.01 ~ 2025.03.31",
    "project_manager": "정동영 소위원장",
    "core_objectives": [
      "과기정통부 및 방송통신위원회, 우주항공청의 예산안을 체계적으로 검토하여 증액/감액 요구사항을 분석",
      "정부와 의원 간 논의 결과를 반영한 예산 조정안 마련",
      "심사 과정의 투명성과 효율성을 확보하여 추경예산 의결을 원활하게 진행"
    ],
    "core_idea": "정부 제출 예산안과 의원 증액 요구사항을 비교 분석하고, 실현 가능성과 정부 운영 방향을 고려한 중립적 조정안을 제시하여 예산의 최적화를 도모",
    "idea_description": "기초연구, 스타이펜드, 방사광가속기 등 과학기술 분야 핵심 사업에 대한 예산 증액 요구사항을 검토하며, 정부의 집행 가능성과 예산 소진율을 고려한 감액 조정을 제안. 또한, 공공요금 인상에 따른 경상비 증액 요구사항에 대한 타당성 검토를 통한 예산 최적화를 추진.",
    "execution_plan": "1단계(2025.01.01~2025.01.15): 예산안 및 증액 요구사항 정리, 관련 부처와의 사전 협의\n2단계(2025.01.16~2025.02.01): 전문위원 보고 및 정부 측 의견 수렴, 의원 의견 분석\n3단계(2025.02.02~2025.02.15): 증액/감액 요구사항에 대한 실현 가능성 평가 및 조정안 마련\n4단계(2025.02.16~2025.03.01): 조정안 검토 및 최종 수정, 추경예산 의결을 위한 보고서 작성\n5단계(2025.03.02~2025.03.31): 심사 결과 공식화 및 관련 부처에 통보",
    "expected_effects": [
      "기대효과 1: 2025년도 과학기술 분야 연구 예산 증액률 15% 이상 확보하여 연구 인프라 강화",
      "기대효과 2: 스타이펜드 사업 증액 요구사항에 대해 72억 원 규모 조정안으로 집행 가능성 확대",
      "기대효과 3: 공공요금 인상에 따른 경상비 증액 요구사항에 대해 102억 원 추가 배정으로 운영 효율성 향상"
    ]
  },
  "metadata": {
    "source_file": "Raw_Data_val/result_제22대국회 제426회(임시회) 제1차 과학기술정보방송통신위원회(예산결산심사소위원회) (2025.06.27.)/05_final_result.json",
    "utterance_count": 662,
    "speakers": [
      "소위원장 정동영",
      "과학기술정보통신부디지털인재양성팀장 성열범",
      "최형두 위원",
      "과학기술정보통신부제1차관 이창윤",
      "방송통신위원회재정팀장 이우혁",
      "이해민 위원",
      "과학기술정보통신부정보보호네트워크정책관 최우혁",
      "전문위원 임명현",
      "우주항공청차장 노경원",
      "방송통신위원회사무처장전담직무대리 김영관",
      "최수진 위원",
      "수석전문위원 이복우",
      "이훈기 위원",
      "박충권 위원",
      "김현 위원",
      "과학기술정보통신부제2차관 강도현"
    ],
    "original_length": 37823,
    "chunking_info": {
      "is_chunked": true,
      "total_chunks": 9
    },
    "is_chunk": true,
    "chunk_index": 1,
    "processing_date": "2025-08-10T22:07:20.286742"
  }
}