{
  "id": "train_088_chunk_1",
  "source_dir": "result_제22대국회 제418회(정기회) 제4차 과학기술정보방송통신위원회(예산결산심사소위원회) (2024.11.14.)",
  "notion_output": "```json\n{\n    \"project_name\": \"2025년도 우주항공청 예산 및 기금운용계획\",\n    \"project_purpose\": \"우주항공청의 2025년도 예산안 및 기금운용계획을 심사하고 확정하여 우주항공 분야의 발전을 도모\",\n    \"project_period\": \"2024.12.01 ~ 2025.01.31\",\n    \"project_manager\": \"노경원 차장\",\n    \"core_objectives\": [\n        \"목표 1: 우주산업 클러스터 인력양성사업 예산 증액 및 세부사업명 변경\",\n        \"목표 2: 초소형위성 개발저변 확대 및 항공인력 교육훈련 예산 수용\",\n        \"목표 3: 우주항공 대외교류 인턴십 및 초중고 우주항공 창의교육 예산 수용\",\n        \"목표 4: 우주과학관 전시시설물 개선 및 가스터빈 관련 예산 증액\",\n        \"목표 5: 우주산업 특화 3D 프린팅 기술 통합지원센터 건립 예산 일부 수용\"\n    ],\n    \"core_idea\": \"우주항공 분야의 인력 양성과 기술 발전을 위한 예산 및 기금운용계획 확정\",\n    \"idea_description\": \"우주항공청의 예산 및 기금운용계획을 통해 우주항공 분야의 인력 양성, 기술 개발, 국제 교류 등을 촉진하고, 관련 기관의 인건비 및 운영비를 조정하여 연구 환경을 개선\",\n    \"execution_plan\": \"1. 우주산업 클러스터 인력양성사업 예산 증액 및 세부사업명 변경 (2024.12.01 ~ 2024.12.15)\\n2. 초소형위성 개발저변 확대 및 항공인력 교육훈련 예산 수용 (2024.12.16 ~ 2024.12.31)\\n3. 우주항공 대외교류 인턴십 및 초중고 우주항공 창의교육 예산 수용 (2025.01.01 ~ 2025.01.15)\\n4. 우주과학관 전시시설물 개선 및 가스터빈 관련 예산 증액 (2025.01.16 ~ 2025.01.31)\\n5. 우주산업 특화 3D 프린팅 기술 통합지원센터 건립 예산 일부 수용 (2025.01.16 ~ 2025.01.31)\",\n    \"expected_effects\": [\n        \"기대효과 1: 우주항공 분야의 전문 인력 양성을 통한 산업 경쟁력 강화\",\n        \"기대효과 2: 초소형위성 및 항공기술 개발을 통한 기술적 우위 확보\",\n        \"기대효과 3: 국제 교류 및 교육 프로그램을 통한 글로벌 협력 강화\"\n    ]\n}\n```",
  "quality_metrics": {
    "final_score": 7.8,
    "is_production_ready": true,
    "iterations_used": 1,
    "is_high_quality": true
  },
  "metadata": {
    "source_file": "../batch_triplet_results/result_제22대국회 제418회(정기회) 제4차 과학기술정보방송통신위원회(예산결산심사소위원회) (2024.11.14.)/05_final_result.json",
    "utterance_count": 2495,
    "original_transcript_length": 142164,
    "speakers": [
      "과학기술정보통신부공공융합연구정책관 이창선",
      "수석전문위원 김건오",
      "방송통신심의위원장 류희림",
      "방송통신위원회혁신기획담당관실 양중배",
      "방송통신위원회혁신기획담당관실 박강욱",
      "최형두 위원",
      "방송통신위원회부위원장 김태규",
      "방송통신위원회대변인 반상권",
      "우주항공청우주과학탐사부문장직무대리 강현우",
      "소위원장 정동영",
      "이훈기 위원",
      "과학기술정보통신부기획조정실장 구혁채",
      "국립과천과학관장 한형주",
      "박충권 위원",
      "우주항공청차장 노경원",
      "방송통신위원회방송정책기획과장 김성환",
      "전문위원 임명현",
      "방송통신위원회운영지원과장 박경주",
      "방송통신위원회방송정책국장 이헌",
      "방송통신위원회기획조정관 김영관",
      "방송통신위원회방송통신이용자정책국장 신영규",
      "김현 위원",
      "최수진 위원",
      "과학기술정보통신부제1차관 이창윤",
      "방송통신위원회사무처장 조성은",
      "과학기술정보통신부제2차관 강도현",
      "이해민 위원",
      "원자력안전위원회사무처장 임승철",
      "원자력안전위원회안전정책국장 조정아"
    ],
    "chunking_info": {
      "is_chunked": true,
      "total_chunks": 32,
      "original_length": 142164
    },
    "is_chunk": true,
    "chunk_info": {
      "chunk_index": 1,
      "total_chunks": 32,
      "chunk_length": 4952
    },
    "dataset_type": "train",
    "processing_date": "2025-08-03T22:14:21.599978"
  }
}