{
  "id": "result_Bed009_chunk_4",
  "source_dir": "result_Bed009",
  "notion_output": {
    "project_name": "DAML-외부서비스 연동형 AI 대화 시스템 개발",
    "project_purpose": "DAML에서 개발 중인 기술을 활용하여 외부 서비스와의 원활한 연동을 통해 더욱 효율적이고 유연한 AI 대화 시스템을 구축",
    "project_period": "2024.01.01 ~ 2024.06.30",
    "project_manager": "Srini",
    "core_objectives": [
      "목표 1: DAML 기술을 활용한 외부 서비스와의 API 연동 구현",
      "목표 2: 다양한 플래너(A/B/C)와의 인터페이스 설계 및 통합",
      "목표 3: 유한 상태 머신 기반의 고속 구문 분석기 개발 및 최적화"
    ],
    "core_idea": "DAML 기술과 외부 서비스의 통합을 통해 AI 대화 시스템의 성능과 유연성을 극대화",
    "idea_description": "DAML에서 개발 중인 기술을 활용하여 외부 서비스와의 원활한 데이터 교환을 가능하게 하고, 다양한 플래너와의 협업을 통해 대화 관리자의 역할을 강화하며, 유한 상태 머신 기반의 구문 분석기를 통해 대규모 데이터 처리 능력을 확보함으로써 AI 대화 시스템의 성능을 향상시킴.",
    "execution_plan": [
      {
        "phase": "1차 개발",
        "description": "DAML 기술과 외부 서비스의 API 연동 구현 및 초기 테스트",
        "duration": "2024.01.01 ~ 2024.02.28",
        "responsible_person": "Srini"
      },
      {
        "phase": "2차 개발",
        "description": "다양한 플래너(A/B/C)와의 인터페이스 설계 및 통합",
        "duration": "2024.03.01 ~ 2024.04.30",
        "responsible_person": "플래너 A/B/C 팀"
      },
      {
        "phase": "3차 개발",
        "description": "유한 상태 머신 기반의 구문 분석기 개발 및 최적화",
        "duration": "2024.05.01 ~ 2024.06.30",
        "responsible_person": "구문 분석기 개발팀"
      }
    ],
    "expected_effects": [
      "기대효과 1: 외부 서비스와의 원활한 데이터 교환을 통해 시스템의 신뢰성 증가",
      "기대효과 2: 다양한 플래너와의 협업을 통한 대화 관리자의 역할 강화",
      "기대효과 3: 구문 분석기의 최적화로 대규모 데이터 처리 속도 향상"
    ]
  },
  "metadata": {
    "source_file": "Raw_Data_val/result_Bed009/05_final_result.json",
    "utterance_count": 691,
    "speakers": [
      "Speaker_A",
      "Speaker_G",
      "Speaker_C",
      "Speaker_D",
      "Speaker_E",
      "Speaker_B",
      "Speaker_F"
    ],
    "original_length": 23895,
    "chunking_info": {
      "is_chunked": true,
      "total_chunks": 6
    },
    "is_chunk": true,
    "chunk_index": 4,
    "processing_date": "2025-08-09T23:33:24.920733"
  }
}