{
  "id": "train_112_chunk_19",
  "source_dir": "result_제22대국회 제427회(임시회) 제3차 기획재정위원회(전체회의) (2025.07.17.)",
  "notion_output": "```json\n{\n    \"project_name\": \"대한민국 경제 혁신 및 지속 가능성 강화 프로젝트\",\n    \"project_purpose\": \"AI 기술과 첨단전략산업 육성을 통해 경제 경쟁력을 강화하고, 부동산시장 안정 및 청년 대출 형평성 문제를 해결하여 지속 가능한 경제 발전을 도모하며, 건설업 및 기타 산업의 투자 활성화를 통해 경제 성장 촉진\",\n    \"project_period\": \"2025.01.01 ~ 2025.12.31\",\n    \"project_manager\": \"구윤철 부총리겸기획재정부장관후보자\",\n    \"core_objectives\": [\n        \"목표 1: AI 기술을 자동차 산업에 접목하여 글로벌 경쟁력 강화\",\n        \"목표 2: 첨단전략산업과 지방 국립대학의 매칭을 통한 인재 양성\",\n        \"목표 3: 비자 제도 개선을 통한 글로벌 인재 유치\",\n        \"목표 4: 부동산시장 안정화를 위한 정책 개발 및 시행\",\n        \"목표 5: 청년 대출제한 규제의 형평성 문제 해결\",\n        \"목표 6: 건설업 투자 활성화를 통한 일자리 창출 및 경제 성장 촉진\"\n    ],\n    \"core_idea\": \"AI와 첨단기술을 활용한 산업 혁신 및 경제 안정화, 건설업 및 기타 산업의 투자 활성화\",\n    \"idea_description\": \"AI를 자동차 산업에 접목하여 자율주행 및 스마트 기능을 강화하고, 첨단전략산업과 교육기관의 협력을 통해 인재를 양성하며, 비자 제도를 개선하여 글로벌 인재를 유치. 또한, 부동산시장 안정화를 위한 정책을 개발하고 청년 대출제한 규제의 형평성 문제를 해결하며, 건설업 투자 활성화를 통해 경제의 지속 가능성을 확보\",\n    \"execution_plan\": \"1단계: AI 기술 연구 및 개발 (2025.01 ~ 2025.06)\\n2단계: 첨단전략산업과 대학의 협력 체계 구축 (2025.03 ~ 2025.09)\\n3단계: 비자 제도 개선 및 시행 (2025.06 ~ 2025.12)\\n4단계: 부동산시장 안정화 정책 개발 및 시행 (2025.04 ~ 2025.12)\\n5단계: 청년 대출제한 규제 형평성 문제 해결 방안 마련 (2025.05 ~ 2025.12)\\n6단계: 건설업 투자 활성화 및 예산 조정 (2025.02 ~ 2025.12)\",\n    \"expected_effects\": [\n        \"기대효과 1: AI 기술 접목을 통한 자동차 산업의 글로벌 시장 점유율 확대\",\n        \"기대효과 2: 첨단기술 분야 인재 양성으로 인한 산업 경쟁력 강화\",\n        \"기대효과 3: 비자 제도 개선으로 인한 글로벌 인재 유입 증가\",\n        \"기대효과 4: 부동산시장 안정화를 통한 경제 안정성 확보\",\n        \"기대효과 5: 청년 대출 형평성 문제 해결로 인한 사회적 신뢰 회복\",\n        \"기대효과 6: 건설업 투자 활성화를 통한 일자리 창출 및 경제 성장 촉진\"\n    ]\n}\n```",
  "quality_metrics": {
    "final_score": 6.2,
    "is_production_ready": false,
    "iterations_used": 3,
    "is_high_quality": false
  },
  "metadata": {
    "source_file": "../batch_triplet_results/result_제22대국회 제427회(임시회) 제3차 기획재정위원회(전체회의) (2025.07.17.)/05_final_result.json",
    "utterance_count": 1930,
    "original_transcript_length": 109213,
    "speakers": [
      "조승래 위원",
      "유상범 위원",
      "차규근 위원",
      "최기상 위원",
      "정태호 위원",
      "안도걸 위원",
      "천하람 위원",
      "김영진 위원",
      "박홍근 위원",
      "김태년 위원",
      "윤영석 위원",
      "이인선 위원",
      "최은석 위원",
      "권영세 위원",
      "박성훈 위원",
      "정일영 위원",
      "오기형 위원",
      "위원장 임이자",
      "부총리겸기획재정부장관후보자 구윤철",
      "진성준 위원",
      "김영환 위원",
      "박대출 위원",
      "박수영 위원"
    ],
    "chunking_info": {
      "is_chunked": true,
      "total_chunks": 25,
      "original_length": 109213
    },
    "is_chunk": true,
    "chunk_info": {
      "chunk_index": 19,
      "total_chunks": 25,
      "chunk_length": 4999
    },
    "dataset_type": "train",
    "processing_date": "2025-08-04T01:55:34.543698"
  }
}