{
  "id": "result_TS3009b_chunk_3",
  "source_dir": "result_TS3009b",
  "notion_output": {
    "raw_text": "**JSON 형식 예시:**\n{\n    \"project_name\": \"프로젝트명\",\n    \"project_purpose\": \"프로젝트의 주요 목적\",\n    \"project_period\": \"예상 수행 기간\",\n    \"project_manager\": \"담당자명\",\n    \"core_objectives\": [\"목표 1\", \"목표 2\", \"목표 3\"],\n    \"core_idea\": \"핵심 아이디어\",\n    \"idea_description\": \"아이디어 설명\",\n    \"execution_plan\": \"실행 계획\",\n    \"expected_effects\": [\"효과 1\", \"효과 2\", \"효과 3\"]\n}\n\n**JSON 예시:**\n{\n    \"project_name\": \"스마트 리모컨 디자인 프로젝트\",\n    \"project_purpose\": \"사용자 중심의 리모컨 디자인 개발을 통해 사용자 경험을 향상시킨다.\",\n    \"project_period\": \"2023년 10월 1일 ~ 2023년 12월 31일\",\n    \"project_manager\": \"디자인 팀장\",\n    \"core_objectives\": [\n        \"사용자 인터페이스의 직관성 향상\",\n        \"리모컨의 기능적 효율성 강화\",\n        \"사용자 맞춤형 경험 제공\"\n    ],\n    \"core_idea\": \"사용자 중심의 디자인 접근법을 바탕으로 리모컨의 사용성을 개선하고, 사용자 맞춤형 기능을 도입하여 사용자 경험을 향상시킨다.\",\n    \"idea_description\": \"이 프로젝트는 사용자 중심의 디자인 접근법을 바탕으로 리모컨의 사용성을 개선하고, 사용자 맞춤형 기능을 도입하여 사용자 경험을 향상시킬 것입니다. 특히, 사용자가 쉽게 이해할 수 있는 인터페이스와 직관적인 제어 기능을 제공함으로써 사용자 만족도를 높이고, 리모컨의 기능적 효율성을 강화할 것입니다.\",\n    \"execution_plan\": \"1. 사용자 조사 및 분석: 사용자 행동 패턴, 니즈, 문제점 분석\\n2. 디자인 개발: 사용자 중심의 디자인 접근법을 바탕으로 UI/UX 개선\\n3. 기능 개발: 사용자 맞춤형 기능 및 직관적인 제어 기능 개발\\n4. 테스트 및 피드백: 사용자 테스트 및 피드백 반영\\n5. 최종 배포: 개선된 리모컨 제품의 최종 배포 및 사용자 교육\",\n    \"expected_effects\": [\n        \"사용자 만족도 향상\",\n        \"리모컨 사용의 효율성 증가\",\n        \"사용자 맞춤형 기능의 도입으로 고객 충성도 향상\"\n    ]\n}\n```\n\n```json\n{\n    \"project_name\": \"사용자 중심 리모컨 디자인 프로젝트\",\n    \"project_purpose\": \"사용자 중심의 디자인 접근법을 바탕으로 리모컨의 사용성을 개선하고, 사용자 맞춤형 기능을 도입하여 사용자 경험을 향상시킨다.\",\n    \"project_period\": \"2023년 11월 1일 ~ 2024년 1월 31일\",\n    \"project_manager\": \"디자인 팀장\",\n    \"core_objectives\": [\n        \"사용자 인터페이스의 직관성 향상\",\n        \"리모컨의 기능적 효율성 강화\",\n        \"사용자 맞춤형 경험 제공\"\n    ],\n    \"core_idea\": \"사용자 중심의 디자인 접근법을 바탕으로 리모컨의 사용성을 개선하고, 사용자 맞춤형 기능을 도입하여 사용자 경험을 향상시킨다.\",\n    \"idea_description\": \"이 프로젝트는 사용자 중심의 디자인 접근법을 바탕으로 리모컨의 사용성을 개선하고, 사용자 맞춤형 기능을 도입하여 사용자 경험을 향상시킬 것입니다. 특히, 사용자가 쉽게 이해할 수 있는 인터페이스와 직관적인 제어 기능을 제공함으로써 사용자 만족도를 높이고, 리모컨의 기능적 효율성을 강화할 것입니다.\",\n    \"execution_plan\":"
  },
  "metadata": {
    "source_file": "../Raw_Data_val/result_TS3009b/05_final_result.json",
    "is_chunk": true,
    "chunk_index": 3,
    "total_chunks": 3,
    "processing_date": "2025-08-10T11:47:04.497700"
  }
}