{
  "id": "result_TS3012c_chunk_3",
  "source_dir": "result_TS3012c",
  "notion_output": {
    "project_name": "노란색 고무 리모컨 디자인 개선 프로젝트",
    "project_purpose": "청소년층을 겨냥한 트렌디한 디자인과 실용성을 결합한 리모컨 개발",
    "project_period": "2025.01.01 ~ 2025.03.31",
    "project_manager": "Speaker_A",
    "core_objectives": [
      "노란색 고무 소재로 제작된 리모컨 디자인 완성",
      "LCD 화면과 곡선 디자인 기능 통합",
      "회사 색상과 트렌디한 디자인 요소 반영"
    ],
    "core_idea": "과일/채소 스타일의 곡선 디자인과 고무 소재를 결합한 젊은 세대를 위한 리모컨",
    "idea_description": "밀라노/파리 트렌드에 영향을 받은 곡선 형태와 고무 소재를 활용한 내구성, 노란색 컬러로 젊은 층의 시선을 끌어당기는 디자인을 구현",
    "execution_plan": [
      "1월: 소재/디자인 조사 (고무 비용 분석, 트렌드 리서치)",
      "2월: 디자인 프로토타이핑 (LCD 통합, 곡선 형태 최적화)",
      "3월: 테스트 및 수정 (사용자 피드백 반영, 색상/재질 최종 결정)"
    ],
    "expected_effects": [
      "리모컨 판매량 30% 증가 (트렌디한 디자인 효과)",
      "고객 만족도 25% 상승 (실용성과 디자인 균형)",
      "브랜드 인지도 15% 향상 (독창적 디자인으로 시각적 인상 강화)"
    ]
  },
  "metadata": {
    "source_file": "Raw_Data_val/result_TS3012c/05_final_result.json",
    "utterance_count": 425,
    "speakers": [
      "Speaker_A",
      "Speaker_D",
      "Speaker_C",
      "Speaker_B"
    ],
    "original_length": 14077,
    "chunking_info": {
      "is_chunked": true,
      "total_chunks": 4
    },
    "is_chunk": true,
    "chunk_index": 3,
    "processing_date": "2025-08-10T22:09:18.279010"
  }
}