{
  "id": "result_제22대국회 제427회(임시회) 제2차 산업통상자원중소벤처기업위원회(전체회의) (2025.07.15.)_chunk_4",
  "source_dir": "result_제22대국회 제427회(임시회) 제2차 산업통상자원중소벤처기업위원회(전체회의) (2025.07.15.)",
  "notion_output": {
    "project_name": "디지털 전환 및 벤처 생태계 강화 프로젝트",
    "project_purpose": "소상공인 및 벤처기업의 디지털 전환을 통해 경쟁력 강화 및 경제 활성화",
    "project_period": "2024.01.01 ~ 2024.12.31",
    "project_manager": "한성숙",
    "core_objectives": [
      "목표 1: 소상공인의 디지털 전환 지원을 통해 경쟁력 강화",
      "목표 2: 벤처기업의 R&D 및 사업화 성공률 향상",
      "목표 3: 지역별 벤처 생태계 구축 및 글로벌 진출 지원"
    ],
    "core_idea": "디지털 전환을 통해 소상공인과 벤처기업의 경쟁력을 강화하고, 지역별 벤처 생태계를 구축하여 경제 활성화를 도모한다.",
    "idea_description": "소상공인과 벤처기업이 디지털 전환을 통해 경쟁력을 강화하고, 지역별로 벤처 생태계를 구축하여 글로벌 진출을 지원한다. 이를 위해 중소기업모태조합의 출자 증액과 벤처투자 유인책을 통해 자금을 확보하며, 지역별로 특화된 R&D 예산을 배분한다.",
    "execution_plan": "1단계: 2024년 1월 - 3월: 디지털 전환 지원 프로그램 개발 및 중소기업모태조합 출자 증액\n2단계: 2024년 4월 - 6월: 벤처기업 R&D 및 사업화 지원 프로그램 시행\n3단계: 2024년 7월 - 9월: 지역별 벤처 생태계 구축 및 글로벌 진출 지원\n4단계: 2024년 10월 - 12월: 성과 평가 및 개선 방안 마련",
    "expected_effects": [
      "기대효과 1: 소상공인의 디지털 전환을 통해 매출 증가 및 경쟁력 강화",
      "기대효과 2: 벤처기업의 R&D 및 사업화 성공률 향상으로 인한 경제 성장",
      "기대효과 3: 지역별 벤처 생태계 구축을 통한 지역경제 활성화"
    ]
  },
  "metadata": {
    "source_file": "Raw_Data_val/result_제22대국회 제427회(임시회) 제2차 산업통상자원중소벤처기업위원회(전체회의) (2025.07.15.)/05_final_result.json",
    "utterance_count": 2167,
    "speakers": [
      "김정호 위원",
      "박지혜 위원",
      "중소벤처기업부장관후보자 한성숙",
      "증인 오세윤",
      "구자근 위원",
      "김종민 위원",
      "송재봉 위원",
      "위원장 이철규",
      "이언주 위원",
      "허성무 위원",
      "김원이 위원",
      "장철민 위원",
      "권향엽 위원",
      "강승규 위원",
      "이종배 위원",
      "나경원 위원",
      "박성민 위원",
      "정동만 위원",
      "김한규 위원",
      "김성원 위원",
      "곽상언 위원",
      "서왕진 위원",
      "정진욱 위원",
      "이재관 위원",
      "박상웅 위원",
      "박형수 위원",
      "허종식 위원",
      "서일준 위원",
      "오세희 위원",
      "김동아 위원"
    ],
    "original_length": 115811,
    "chunking_info": {
      "is_chunked": true,
      "total_chunks": 26
    },
    "is_chunk": true,
    "chunk_index": 4,
    "processing_date": "2025-08-09T23:04:43.850939"
  }
}