{
  "id": "train_219_chunk_1",
  "source_dir": "result_ES2013d",
  "notion_output": "```json\n{\n    \"project_name\": \"바나나 모양 리모컨 개발 프로젝트\",\n    \"project_purpose\": \"사용자 친화적이고 혁신적인 리모컨 디자인 개발\",\n    \"project_period\": \"2023.11.01 ~ 2024.01.31\",\n    \"project_manager\": \"Speaker_A\",\n    \"core_objectives\": [\n        \"목표 1: 바나나 모양의 리모컨 프로토타입 개발\",\n        \"목표 2: 사용자 요구 사항 및 마케팅 트렌드 반영한 디자인 평가\",\n        \"목표 3: 비용 효율적인 재료 선택 및 생산 계획 수립\"\n    ],\n    \"core_idea\": \"바나나 모양의 리모컨을 통해 사용자의 편의성과 디자인 혁신을 동시에 추구\",\n    \"idea_description\": \"바나나 모양의 곡선형 디자인을 통해 잡기 편하고, 스크롤 푸시 버튼 기술을 활용하여 직관적인 사용성을 제공. 디자인은 심플하면서도 트렌디한 요소를 포함하여 시장에서의 차별화 가능성을 높임.\",\n    \"execution_plan\": \"1. 프로토타입 개발 (2023.11.01 ~ 2023.11.30)\\n2. 사용자 및 마케팅 트렌드 반영한 디자인 평가 (2023.12.01 ~ 2023.12.15)\\n3. 재료 선택 및 비용 분석 (2023.12.16 ~ 2023.12.31)\\n4. 최종 디자인 확정 및 생산 계획 수립 (2024.01.01 ~ 2024.01.15)\\n5. 생산 및 출시 준비 (2024.01.16 ~ 2024.01.31)\",\n    \"expected_effects\": [\n        \"기대효과 1: 사용자 친화적인 디자인을 통한 시장 점유율 확대\",\n        \"기대효과 2: 혁신적인 디자인으로 브랜드 이미지 강화\",\n        \"기대효과 3: 비용 효율적인 생산을 통한 수익성 향상\"\n    ]\n}\n```",
  "quality_metrics": {
    "final_score": 7.8,
    "is_production_ready": true,
    "iterations_used": 1,
    "is_high_quality": true
  },
  "metadata": {
    "source_file": "../batch_triplet_results/result_ES2013d/05_final_result.json",
    "utterance_count": 253,
    "original_transcript_length": 9302,
    "speakers": [
      "Speaker_C",
      "Speaker_A",
      "Speaker_D",
      "Speaker_B"
    ],
    "chunking_info": {
      "is_chunked": true,
      "total_chunks": 2,
      "original_length": 9302
    },
    "is_chunk": true,
    "chunk_info": {
      "chunk_index": 1,
      "total_chunks": 2,
      "chunk_length": 4989
    },
    "dataset_type": "train",
    "processing_date": "2025-08-04T06:29:04.586490"
  }
}