{
  "id": "result_제22대국회 제427회(임시회) 제2차 농림축산식품해양수산위원회(전체회의) (2025.07.14.)_chunk_13",
  "source_dir": "result_제22대국회 제427회(임시회) 제2차 농림축산식품해양수산위원회(전체회의) (2025.07.14.)",
  "notion_output": {
    "project_name": "해양수산부 부산 이전 및 녹색해운항로 구축 전략 개발",
    "project_purpose": "해양수산부의 부산 이전과 녹색해운항로 구축을 위한 전략적 계획 수립 및 실행",
    "project_period": "2025.01.01 ~ 2025.03.31",
    "project_manager": "해양수산부장관후보자 전재수",
    "core_objectives": [
      "부산 이전에 따른 예산 및 인력 확충 전략 수립",
      "녹색해운항로 구축에 대한 법적·정책적 준비",
      "해운 탄소세 부과 및 수익화 방안 수립",
      "소금산업진흥연구센터 운영 및 R&D 활성화 계획",
      "국민적 우려 사항 대응 및 정책금융 재편 방안"
    ],
    "core_idea": "부산 이전과 녹색해운항로 구축을 위한 전략적 계획을 수립하여, 기존의 수익이 없는 항로를 민간과 협력하여 수익화하고, 탄소세 부과를 통해 수익 창출하며, 연구센터를 통해 소금산업의 R&D 기반을 강화하는 다각적 접근",
    "idea_description": "부산 이전은 국가 전략적 성장과 관련된 중요한 과제로, 예산 증가와 인력 확충이 필요하다. 녹색해운항로 구축은 환경 보호와 경제 성장을 동시에 이끌 수 있는 방안으로, 법적·정책적 준비를 통해 실현해야 한다. 해운 탄소세는 수익 창출을 위한 필수 조치이며, 연구센터는 소금산업의 기술 발전을 지원해야 한다. 이 모든 요소를 종합적으로 계획하여 실행해야 한다.",
    "execution_plan": [
      {
        "phase": "초기 분석 및 조사",
        "tasks": [
          "부산 이전에 따른 예산 및 인력 확충 분석",
          "녹색해운항로 구축에 대한 법적·정책적 준비",
          "해운 탄소세 부과 방안 수립",
          "소금산업진흥연구센터 현황 점검"
        ],
        "deadline": "2025.01.15"
      },
      {
        "phase": "정책 및 예산 수립",
        "tasks": [
          "부산 이전에 따른 예산 책정 및 공개",
          "녹색해운항로 구축에 대한 법적 조치 마련",
          "해운 탄소세 부과 정책 수립",
          "소금산업진흥연구센터 운영 방안 수립"
        ],
        "deadline": "2025.02.01"
      },
      {
        "phase": "실행 및 모니터링",
        "tasks": [
          "부산 이전 및 녹색해운항로 구축 실행",
          "해운 탄소세 수익화 모니터링",
          "소금산업진흥연구센터 운영 개선",
          "국민적 우려 사항 대응 및 정책금융 재편"
        ],
        "deadline": "2025.03.31"
      }
    ],
    "expected_effects": [
      "부산 이전에 따른 예산 증가 및 인력 확충으로 경영 효율성 향상",
      "녹색해운항로 구축으로 환경 보호 및 경제 성장 촉진",
      "해운 탄소세 부과로 수익 창출 및 재정 안정",
      "소금산업진흥연구센터 운영으로 R&D 기반 강화",
      "국민적 우려 사항 대응으로 신뢰도 향상 및 정책적 지지 확보"
    ]
  },
  "metadata": {
    "source_file": "Raw_Data_val/result_제22대국회 제427회(임시회) 제2차 농림축산식품해양수산위원회(전체회의) (2025.07.14.)/05_final_result.json",
    "utterance_count": 1700,
    "speakers": [
      "윤준병 위원",
      "참고인 이상국",
      "서천호 위원",
      "문대림 위원",
      "송옥주 위원",
      "임호선 위원",
      "농림축산식품부장관 송미령",
      "문금주 위원",
      "이원택 위원",
      "전종덕 위원",
      "해양수산부장관후보자 전재수",
      "조승환 위원",
      "이만희 위원",
      "조경태 위원",
      "정희용 위원",
      "김선교 위원",
      "임미애 위원",
      "이병진 위원",
      "주철현 위원",
      "소위원장 이원택",
      "위원장 어기구",
      "강명구 위원",
      "서삼석 위원"
    ],
    "original_length": 102617,
    "chunking_info": {
      "is_chunked": true,
      "total_chunks": 23
    },
    "is_chunk": true,
    "chunk_index": 13,
    "processing_date": "2025-08-10T22:33:46.877108"
  }
}