{
  "id": "result_제22대국회 제427회(임시회) 제2차 산업통상자원중소벤처기업위원회(전체회의) (2025.07.15.)_chunk_3",
  "source_dir": "result_제22대국회 제427회(임시회) 제2차 산업통상자원중소벤처기업위원회(전체회의) (2025.07.15.)",
  "notion_output": {
    "project_name": "인사청문회 자료 제출 및 관리 프로젝트",
    "project_purpose": "인사청문회 과정에서 발생한 자료 제출 지연 및 증인 불출석 문제를 체계적으로 관리하여 투명성과 절차 준수를 확보하는 프로젝트",
    "project_period": "2025.01.01 ~ 2025.03.31",
    "project_manager": "이철규 위원장",
    "core_objectives": [
      "중기부가 요구한 자료(소상공인정책자금 원금 감면 보고서)의 제출 지연 사유 및 해결 방안 검토",
      "외환거래 내역 등 40건 미제출 자료의 조사 및 제출 일정 확정",
      "증인 최인혁의 해외출장 계획과 청문회 불출석 사유에 대한 사실관계 명확화"
    ],
    "core_idea": "청문회 자료 제출 의무사항 준수 및 증인 관리 프로세스 개선을 통한 공정성 확보",
    "idea_description": "국회 인사청문회 과정에서 발생한 자료 미제출 및 증인 불출석 문제를 체계적으로 관리하고, 관련 법규와 절차에 따라 처리 방안을 마련하여 투명성과 공정성을 강화하는 프로젝트",
    "execution_plan": [
      "2025.01.10: 중기부 자료 제출 지연 사유 확인 및 법적 근거 분석",
      "2025.01.15: 서면 요청을 통한 40건 미제출 자료 현황 조사",
      "2025.01.20: 증인 최인혁의 해외출장 계획과 청문회 일정 간 충돌 여부 검토",
      "2025.01.25: 자료 제출 마감일(오전) 전까지 관련 부서와의 협의 및 처리 결과 보고"
    ],
    "expected_effects": [
      "2025.02.01까지 모든 청문회 자료 제출 완료로 법적 문제 예방",
      "증인 관리 프로세스 개선으로 향후 인사청문회 절차 투명성 확보",
      "청문회 관련 40건 미제출 자료의 80% 이상 해결로 신뢰도 향상"
    ]
  },
  "metadata": {
    "source_file": "Raw_Data_val/result_제22대국회 제427회(임시회) 제2차 산업통상자원중소벤처기업위원회(전체회의) (2025.07.15.)/05_final_result.json",
    "utterance_count": 2167,
    "speakers": [
      "김원이 위원",
      "위원장 이철규",
      "나경원 위원",
      "김성원 위원",
      "김정호 위원",
      "장철민 위원",
      "이재관 위원",
      "박성민 위원",
      "이언주 위원",
      "박형수 위원",
      "허성무 위원",
      "김종민 위원",
      "서일준 위원",
      "김동아 위원",
      "중소벤처기업부장관후보자 한성숙",
      "박지혜 위원",
      "정진욱 위원",
      "오세희 위원",
      "허종식 위원",
      "곽상언 위원",
      "정동만 위원",
      "서왕진 위원",
      "송재봉 위원",
      "박상웅 위원",
      "강승규 위원",
      "이종배 위원",
      "권향엽 위원",
      "김한규 위원",
      "구자근 위원",
      "증인 오세윤"
    ],
    "original_length": 115811,
    "chunking_info": {
      "is_chunked": true,
      "total_chunks": 26
    },
    "is_chunk": true,
    "chunk_index": 3,
    "processing_date": "2025-08-10T22:02:21.421580"
  }
}