{
  "id": "result_제22대국회 제427회(임시회) 제2차 외교통일위원회(전체회의) (2025.07.14.)_chunk_19",
  "source_dir": "result_제22대국회 제427회(임시회) 제2차 외교통일위원회(전체회의) (2025.07.14.)",
  "notion_output": {
    "project_name": "북한 인권 및 통일 정책 개선 프로젝트",
    "project_purpose": "북한 인권 문제와 통일 정책을 중심으로 한 법안 개선 및 정책 실행을 통해 민주주의와 평화를 위한 협력과 개혁을 추진하는 프로젝트",
    "project_period": "2024년 6월 ~ 2025년 12월",
    "project_manager": "정동영 통일부장관후보자",
    "core_objectives": [
      "북한 인권 관련 법안 개정을 통해 인권 문제를 해결하고, 통일 정책의 공정성을 확보",
      "민주당 통일부장관 후보자 정동영의 정치적 성향과 개혁적 사고를 반영한 정책 제안",
      "국내외의 평화와 통일을 위한 협력과 합의를 도출"
    ],
    "core_idea": "북한 인권과 통일 정책을 결합한 법안 개선 및 정책 실행을 통해 민주주의와 평화를 위한 협력과 개혁을 추진",
    "idea_description": "이 프로젝트는 북한 인권 문제와 통일 정책을 중심으로 한 법안 개선을 통해 민주주의와 평화를 위한 협력과 개혁을 추진합니다. 이는 북한 인권 법의 개정을 통해 인권 문제를 해결하고, 통일 정책의 공정성을 확보하며, 민주당 통일부장관 후보자 정동영의 정치적 성향과 개혁적 사고를 반영한 정책 제안을 통해 평화와 통일을 위한 협력과 합의를 도출합니다.",
    "execution_plan": [
      "2024년 6월: 북한 인권 법 개정안 발의 및 논의",
      "2024년 7월: 법안 검토 및 수정",
      "2024년 8월: 법안 통과 및 시행",
      "2024년 9월: 통일 정책 실행 계획 수립",
      "2024년 10월: 정책 실행 및 평가",
      "2025년 12월: 프로젝트 종료 및 성과 발표"
    ],
    "expected_effects": [
      "북한 인권 문제 해결을 위한 법안 개정으로 인한 인권 개선",
      "통일 정책의 공정성과 신뢰성 향상",
      "민주당 통일부장관 후보자 정동영의 정치적 성향과 개혁적 사고 반영된 정책 제안",
      "국내외의 평화와 통일 협력과 합의 도출",
      "프로젝트 수행 기간 동안의 성과와 평가"
    ]
  },
  "metadata": {
    "source_file": "../Raw_Data_val/result_제22대국회 제427회(임시회) 제2차 외교통일위원회(전체회의) (2025.07.14.)/05_final_result.json",
    "is_chunk": true,
    "chunk_index": 19,
    "total_chunks": 27,
    "processing_date": "2025-08-10T11:34:28.689576"
  }
}